mcp_tmux/__init__.py
mcp_tmux/server.py
mcp_tmux/tmux_manager.py
mcp_tmux/utils.py
mcp_tmux_server-0.1.2.dist-info/METADATA
mcp_tmux_server-0.1.2.dist-info/WHEEL
mcp_tmux_server-0.1.2.dist-info/entry_points.txt
mcp_tmux_server-0.1.2.dist-info/RECORD
