Metadata-Version: 2.4
Name: mcp-tmux-server
Version: 0.1.2
Summary: MCP server for interactive tmux terminal sessions with Claude Code
Author: Grigori Kartashyan
Author-email: grigori.kartashyan@gmail.com
Requires-Python: >=3.10,<4.0
Classifier: Programming Language :: Python :: 3
Classifier: Programming Language :: Python :: 3.10
Classifier: Programming Language :: Python :: 3.11
Classifier: Programming Language :: Python :: 3.12
Classifier: Programming Language :: Python :: 3.13
Classifier: Programming Language :: Python :: 3.14
Requires-Dist: mcp[cli] (>=1.2.0,<2.0.0)
